tristero/__init__.py
tristero/api.py
tristero/client.py
tristero/config.py
tristero/files/__init__.py
tristero/files/erc20_abi.json
tristero/files/permit2_abi.json
tristero/permit2.py
tristero/py.typed
tristero-0.1.5.dist-info/WHEEL
tristero-0.1.5.dist-info/METADATA
tristero-0.1.5.dist-info/RECORD
