Metadata-Version: 2.3
Name: tristero
Version: 0.1.5
Summary: Library for trading on Tristero
Author: pty1
Author-email: pty1 <pty11@proton.me>
Requires-Dist: eth-account>=0.13.7
Requires-Dist: httpx>=0.28.1
Requires-Dist: pydantic>=2.12.4
Requires-Dist: tenacity>=9.1.2
Requires-Dist: web3>=7.14.0
Requires-Dist: websockets>=15.0.1
Requires-Python: >=3.10
